README.md
setup.cfg
setup.py
ecgxai/__init__.py
ecgxai.egg-info/PKG-INFO
ecgxai.egg-info/SOURCES.txt
ecgxai.egg-info/dependency_links.txt
ecgxai.egg-info/requires.txt
ecgxai.egg-info/top_level.txt
ecgxai/network/__init__.py
ecgxai/network/causalcnn/__init__.py
ecgxai/network/causalcnn/decoder.py
ecgxai/network/causalcnn/encoder.py
ecgxai/network/causalcnn/modules.py
ecgxai/network/causalcnn/vae.py
ecgxai/network/doubleresidual/__init__.py
ecgxai/network/doubleresidual/modules.py
ecgxai/systems/AE_system.py
ecgxai/systems/VAE_system.py
ecgxai/systems/__init__.py
ecgxai/systems/base_system.py
ecgxai/systems/classification_system.py
ecgxai/utils/__init__.py
ecgxai/utils/dataset.py
ecgxai/utils/exceptions.py
ecgxai/utils/loss.py
ecgxai/utils/metrics.py
ecgxai/utils/transforms.py