Metadata-Version: 2.1
Name: ecgxai
Version: 0.1.0
Summary: Neatly packaged AI methods for ECG analysis
Home-page: https://github.com/rutgervandeleur/ecgxai
Author: Rutger van de Leur
Author-email: r.r.vandeleur@umcutrecht.nl
License: GNU AGPLv3
Platform: UNKNOWN
